sipcounter.py
sipcounter-0.0.2.dist-info/LICENSE.txt
sipcounter-0.0.2.dist-info/METADATA
sipcounter-0.0.2.dist-info/WHEEL
sipcounter-0.0.2.dist-info/top_level.txt
sipcounter-0.0.2.dist-info/RECORD
