Metadata-Version: 2.1
Name: sipcounter
Version: 0.0.2
Summary: SIP message counter
Home-page: https://github.com/sszokoly/sipcounter
Author: Szabolcs Szokoly
Author-email: szokoly@protonmail.com
Maintainer: Szabolcs Szokoly
Maintainer-email: sszokoly@protonmail.com
License: MIT
Keywords: VoIP telephony SIP protocol message counter
Platform: UNKNOWN
Classifier: Environment :: Console
Classifier: Development Status :: 4 - Beta
Classifier: Intended Audience :: Developers
Classifier: Topic :: Communications :: Telephony
Classifier: Programming Language :: Python :: 3
Classifier: Programming Language :: Python :: 2.7
Classifier: Operating System :: OS Independent
Classifier: License :: OSI Approved :: MIT License
Requires-Python: >=2.7
